pptxtoimages/__init__.py
pptxtoimages/tools/__init__.py
pptxtoimages/tools/convert.py
pptxtoimages-0.1.14.dist-info/LICENSE
pptxtoimages-0.1.14.dist-info/METADATA
pptxtoimages-0.1.14.dist-info/WHEEL
pptxtoimages-0.1.14.dist-info/entry_points.txt
pptxtoimages-0.1.14.dist-info/top_level.txt
pptxtoimages-0.1.14.dist-info/RECORD
