Metadata-Version: 2.1
Name: pptxtoimages
Version: 0.1.14
Summary: Convert .pptx presentations to image files easily.
Author: Burak Civelek
License: MIT
Project-URL: Documentation, https://github.com/brkcvlk/pptxtoimages#readme
Project-URL: Source, https://github.com/brkcvlk/pptxtoimages
Project-URL: Bug Report, https://github.com/brkcvlk/pptxtoimages/issues
Project-URL: Download Stats, https://pepy.tech/project/pptxtoimages
Keywords: pptx,converter,slides,images,python
Classifier: Programming Language :: Python :: 3
Classifier: License :: OSI Approved :: MIT License
Classifier: Operating System :: OS Independent
Requires-Python: >=3.7
License-File: LICENSE
Requires-Dist: pdf2image
